projects/mux_2to1/rtl/mux_2to1.v
module mux_2to1 #(
    parameter WIDTH = 8
) (
    input  wire [WIDTH-1:0] in0,
    input  wire [WIDTH-1:0] in1,
    input  wire             sel,
    output wire [WIDTH-1:0] out
);

    assign out = sel ? in1 : in0;

endmodule

projects/mux_2to1/tb/tb_mux_2to1.v
`timescale 1ns/1ps

module tb_mux_2to1;

    parameter WIDTH = 8;

    reg  [WIDTH-1:0] tb_in0;
    reg  [WIDTH-1:0] tb_in1;
    reg              tb_sel;
    wire [WIDTH-1:0] tb_out;

    // Instantiate design under test (DUT)
    mux_2to1 #(
        .WIDTH(WIDTH)
    ) dut (
        .in0(tb_in0),
        .in1(tb_in1),
        .sel(tb_sel),
        .out(tb_out)
    );

    // Expected value helper
    reg [WIDTH-1:0] expected_out;
    integer i, j, k;
    integer error_count;

    initial begin
        // Waveform setup
        $dumpfile("../wave/mux_2to1.vcd");
        $dumpvars(0, tb_mux_2to1);

        error_count = 0;
        
        // Initialize inputs
        tb_in0 = 0;
        tb_in1 = 0;
        tb_sel = 0;
        
        #10;

        // Exhaustive test for select and typical values
        for (i = 0; i < 4; i = i + 1) begin
            for (j = 0; j < 4; j = j + 1) begin
                for (k = 0; k < 2; k = k + 1) begin
                    tb_in0 = i * 8'h55; // Generate varying patterns (0x00, 0x55, 0xAA, 0xFF)
                    tb_in1 = j * 8'h33; // Generate varying patterns (0x00, 0x33, 0x66, 0x99)
                    tb_sel = k;
                    
                    #10;
                    
                    // Compute expected output
                    expected_out = tb_sel ? tb_in1 : tb_in0;
                    
                    // Check output
                    if (tb_out !== expected_out) begin
                        $display("[ERROR] at time %0t: sel=%b, in0=0x%h, in1=0x%h | Expected out=0x%h, Got out=0x%h", 
                                 $time, tb_sel, tb_in0, tb_in1, expected_out, tb_out);
                        error_count = error_count + 1;
                    end
                end
            end
        end

        #10;
        if (error_count == 0) begin
            $display("[SUCCESS] All tests passed! VCD generated successfully.");
        end else begin
            $display("[FAILURE] %d mismatches found during simulation.", error_count);
        end

        $finish;
    end

endmodule

projects/mux_2to1/wave/mux_2to1.vcd
$date
	Mon Jul 06 13:01:34 2026
$end
$version
	Icarus Verilog
$end
$timescale
	1ps
$end
$scope module tb_mux_2to1 $end
$var wire 8 ! tb_out [7:0] $end
$var parameter 32 " WIDTH $end
$var reg 8 # expected_out [7:0] $end
$var reg 8 $ tb_in0 [7:0] $end
$var reg 8 % tb_in1 [7:0] $end
$var reg 1 & tb_sel $end
$var integer 32 ' error_count [31:0] $end
$var integer 32 ( i [31:0] $end
$var integer 32 ) j [31:0] $end
$var integer 32 * k [31:0] $end
$scope module dut $end
$var wire 8 + in0 [7:0] $end
$var wire 8 , in1 [7:0] $end
$var wire 1 & sel $end
$var wire 8 - out [7:0] $end
$var parameter 32 . WIDTH $end
$upscope $end
$upscope $end
$enddefinitions $end
$comment Show the parameter values. $end
$dumpall
b1000 .
b1000 "
$end
#0
$dumpvars
b0 -
b0 ,
b0 +
bx *
bx )
bx (
b0 '
0&
b0 %
b0 $
bx #
b0 !
$end
#10000
b0 *
b0 )
b0 (
#20000
1&
b1 *
b0 #
#30000
0&
b110011 %
b110011 ,
b1 )
b0 *
#40000
b110011 !
b110011 -
1&
b1 *
#50000
b0 !
b0 -
0&
b1100110 %
b1100110 ,
b10 )
b0 *
b110011 #
#60000
b1100110 !
b1100110 -
1&
b1 *
b0 #
#70000
b0 !
b0 -
0&
b10011001 %
b10011001 ,
b11 )
b0 *
b1100110 #
#80000
b10011001 !
b10011001 -
1&
b1 *
b0 #
#90000
b1010101 !
b1010101 -
0&
b0 %
b0 ,
b1010101 $
b1010101 +
b1 (
b0 )
b0 *
b10011001 #
#100000
b0 !
b0 -
1&
b1 *
b1010101 #
#110000
b1010101 !
b1010101 -
0&
b110011 %
b110011 ,
b1 )
b0 *
b0 #
#120000
b110011 !
b110011 -
1&
b1 *
b1010101 #
#130000
b1010101 !
b1010101 -
0&
b1100110 %
b1100110 ,
b10 )
b0 *
b110011 #
#140000
b1100110 !
b1100110 -
1&
b1 *
b1010101 #
#150000
b1010101 !
b1010101 -
0&
b10011001 %
b10011001 ,
b11 )
b0 *
b1100110 #
#160000
b10011001 !
b10011001 -
1&
b1 *
b1010101 #
#170000
b10101010 !
b10101010 -
0&
b0 %
b0 ,
b10101010 $
b10101010 +
b10 (
b0 )
b0 *
b10011001 #
#180000
b0 !
b0 -
1&
b1 *
b10101010 #
#190000
b10101010 !
b10101010 -
0&
b110011 %
b110011 ,
b1 )
b0 *
b0 #
#200000
b110011 !
b110011 -
1&
b1 *
b10101010 #
#210000
b10101010 !
b10101010 -
0&
b1100110 %
b1100110 ,
b10 )
b0 *
b110011 #
#220000
b1100110 !
b1100110 -
1&
b1 *
b10101010 #
#230000
b10101010 !
b10101010 -
0&
b10011001 %
b10011001 ,
b11 )
b0 *
b1100110 #
#240000
b10011001 !
b10011001 -
1&
b1 *
b10101010 #
#250000
b11111111 !
b11111111 -
0&
b0 %
b0 ,
b11111111 $
b11111111 +
b11 (
b0 )
b0 *
b10011001 #
#260000
b0 !
b0 -
1&
b1 *
b11111111 #
#270000
b11111111 !
b11111111 -
0&
b110011 %
b110011 ,
b1 )
b0 *
b0 #
#280000
b110011 !
b110011 -
1&
b1 *
b11111111 #
#290000
b11111111 !
b11111111 -
0&
b1100110 %
b1100110 ,
b10 )
b0 *
b110011 #
#300000
b1100110 !
b1100110 -
1&
b1 *
b11111111 #
#310000
b11111111 !
b11111111 -
0&
b10011001 %
b10011001 ,
b11 )
b0 *
b1100110 #
#320000
b10011001 !
b10011001 -
1&
b1 *
b11111111 #
#330000
b100 (
b100 )
b10 *
b10011001 #
