libraries/rtl/mux_2to1_modified.v
// Reusable 2:1 Multiplexer
// Non-parameterized, purely combinational implementation using continuous assignment.

module mux_2to1_modified (
    input  wire in0,
    input  wire in1,
    input  wire sel,
    output wire out
);

    // Continuous assignment implementing the multiplexer logic
    assign out = sel ? in1 : in0;

endmodule

projects/mux_2to1_modified/tb/tb_mux_2to1_modified.v
`timescale 1ns/1ps

module tb_mux_2to1_modified;

    // Testbench signals
    reg  tb_in0;
    reg  tb_in1;
    reg  tb_sel;
    wire tb_out;

    // Instantiate design under test (DUT)
    mux_2to1_modified dut (
        .in0(tb_in0),
        .in1(tb_in1),
        .sel(tb_sel),
        .out(tb_out)
    );

    // Expected value helper
    reg expected_out;
    integer i;
    integer error_count;

    initial begin
        // Waveform setup
        $dumpfile("../wave/mux_2to1_modified.vcd");
        $dumpvars(0, tb_mux_2to1_modified);

        error_count = 0;
        
        // Initialize inputs
        tb_in0 = 0;
        tb_in1 = 0;
        tb_sel = 0;
        
        #10;

        // Exhaustive test for all 8 possible input combinations (2^3 = 8)
        for (i = 0; i < 8; i = i + 1) begin
            // Deconstruct iteration variable into inputs
            tb_in0 = i[0];
            tb_in1 = i[1];
            tb_sel = i[2];
            
            #10;
            
            // Compute expected output
            expected_out = tb_sel ? tb_in1 : tb_in0;
            
            // Check output
            if (tb_out !== expected_out) begin
                $display("[ERROR] at time %0t: sel=%b, in0=%b, in1=%b | Expected out=%b, Got out=%b", 
                         $time, tb_sel, tb_in0, tb_in1, expected_out, tb_out);
                error_count = error_count + 1;
            end else begin
                $display("[INFO] at time %0t: sel=%b, in0=%b, in1=%b | Expected out=%b, Got out=%b (PASS)", 
                         $time, tb_sel, tb_in0, tb_in1, expected_out, tb_out);
            end
        end

        #10;
        if (error_count == 0) begin
            $display("[SUCCESS] All 8 test cases passed! VCD generated successfully.");
        end else begin
            $display("[FAILURE] %d mismatches found during simulation.", error_count);
        end

        $finish;
    end

endmodule

projects/mux_2to1_modified/wave/mux_2to1_modified.vcd
$date
	Tue Jul 07 08:34:58 2026
$end
$version
	Icarus Verilog
$end
$timescale
	1ps
$end
$scope module tb_mux_2to1_modified $end
$var wire 1 ! tb_out $end
$var reg 1 " expected_out $end
$var reg 1 # tb_in0 $end
$var reg 1 $ tb_in1 $end
$var reg 1 % tb_sel $end
$var integer 32 & error_count [31:0] $end
$var integer 32 ' i [31:0] $end
$scope module dut $end
$var wire 1 # in0 $end
$var wire 1 $ in1 $end
$var wire 1 % sel $end
$var wire 1 ! out $end
$upscope $end
$upscope $end
$enddefinitions $end
$comment Show the parameter values. $end
$dumpall
$end
#0
$dumpvars
bx '
b0 &
0%
0$
0#
x"
0!
$end
#10000
b0 '
#20000
1!
1#
b1 '
0"
#30000
0!
1$
0#
b10 '
1"
#40000
1!
1#
b11 '
0"
#50000
0!
1%
0$
0#
b100 '
1"
#60000
1#
b101 '
0"
#70000
1!
1$
0#
b110 '
#80000
1#
b111 '
1"
#90000
b1000 '
